{
	"particles": [
		{
			"id": "1",
			"position": {
				"vector": [
					419.0113639831543,
					289.0539779663086
				]
			}
		},
		{
			"id": "2",
			"position": {
				"vector": [
					390.0113639831543,
					308.0539779663086
				]
			}
		},
		{
			"id": "3",
			"position": {
				"vector": [
					373.0113639831543,
					330.0539779663086
				]
			}
		},
		{
			"id": "4",
			"position": {
				"vector": [
					384.0113639831543,
					355.0539779663086
				]
			}
		},
		{
			"id": "5",
			"position": {
				"vector": [
					420.0113639831543,
					360.0539779663086
				]
			}
		},
		{
			"id": "6",
			"position": {
				"vector": [
					449.0113639831543,
					336.0539779663086
				]
			}
		},
		{
			"id": "7",
			"position": {
				"vector": [
					474.0113639831543,
					359.0539779663086
				]
			}
		},
		{
			"id": "8",
			"position": {
				"vector": [
					511.0113639831543,
					352.0539779663086
				]
			}
		},
		{
			"id": "9",
			"position": {
				"vector": [
					518.0113639831543,
					326.0539779663086
				]
			}
		},
		{
			"id": "10",
			"position": {
				"vector": [
					500.0113639831543,
					307.0539779663086
				]
			}
		},
		{
			"id": "11",
			"position": {
				"vector": [
					473.0113639831543,
					288.0539779663086
				]
			}
		},
		{
			"id": "12",
			"position": {
				"vector": [
					472.0113639831543,
					247.0539779663086
				]
			}
		},
		{
			"id": "13",
			"position": {
				"vector": [
					473.0113639831543,
					214.0539779663086
				]
			}
		},
		{
			"id": "14",
			"position": {
				"vector": [
					472.0113639831543,
					167.0539779663086
				]
			}
		},
		{
			"id": "15",
			"position": {
				"vector": [
					455.0113639831543,
					144.0539779663086
				]
			}
		},
		{
			"id": "16",
			"position": {
				"vector": [
					431.0113639831543,
					144.0539779663086
				]
			}
		},
		{
			"id": "17",
			"position": {
				"vector": [
					420.0113639831543,
					168.0539779663086
				]
			}
		},
		{
			"id": "18",
			"position": {
				"vector": [
					417.0113639831543,
					210.0539779663086
				]
			}
		},
		{
			"id": "19",
			"position": {
				"vector": [
					417.0113639831543,
					248.0539779663086
				]
			}
		}
	],
	"springs": [
		{
			"id": "1",
			"particles": [
				{
					"id": "16",
					"position": {
						"vector": [
							431.0113639831543,
							144.0539779663086
						]
					},
					"springIds": [
						"1",
						"19",
						"30"
					],
					"bodyIds": [
						"1"
					]
				},
				{
					"id": "15",
					"position": {
						"vector": [
							455.0113639831543,
							144.0539779663086
						]
					},
					"springIds": [
						"1",
						"2",
						"29"
					],
					"bodyIds": [
						"1"
					]
				}
			]
		},
		{
			"id": "2",
			"particles": [
				{
					"id": "15",
					"position": {
						"vector": [
							455.0113639831543,
							144.0539779663086
						]
					},
					"springIds": [
						"1",
						"2",
						"29"
					],
					"bodyIds": [
						"1"
					]
				},
				{
					"id": "14",
					"position": {
						"vector": [
							472.0113639831543,
							167.0539779663086
						]
					},
					"springIds": [
						"2",
						"3",
						"27",
						"30",
						"33"
					],
					"bodyIds": [
						"1"
					]
				}
			]
		},
		{
			"id": "3",
			"particles": [
				{
					"id": "14",
					"position": {
						"vector": [
							472.0113639831543,
							167.0539779663086
						]
					},
					"springIds": [
						"2",
						"3",
						"27",
						"30",
						"33"
					],
					"bodyIds": [
						"1"
					]
				},
				{
					"id": "13",
					"position": {
						"vector": [
							473.0113639831543,
							214.0539779663086
						]
					},
					"springIds": [
						"3",
						"4",
						"25",
						"28",
						"32"
					],
					"bodyIds": [
						"1"
					]
				}
			]
		},
		{
			"id": "4",
			"particles": [
				{
					"id": "13",
					"position": {
						"vector": [
							473.0113639831543,
							214.0539779663086
						]
					},
					"springIds": [
						"3",
						"4",
						"25",
						"28",
						"32"
					],
					"bodyIds": [
						"1"
					]
				},
				{
					"id": "12",
					"position": {
						"vector": [
							472.0113639831543,
							247.0539779663086
						]
					},
					"springIds": [
						"4",
						"5",
						"23",
						"26",
						"31"
					],
					"bodyIds": [
						"1"
					]
				}
			]
		},
		{
			"id": "5",
			"particles": [
				{
					"id": "12",
					"position": {
						"vector": [
							472.0113639831543,
							247.0539779663086
						]
					},
					"springIds": [
						"4",
						"5",
						"23",
						"26",
						"31"
					],
					"bodyIds": [
						"1"
					]
				},
				{
					"id": "11",
					"position": {
						"vector": [
							473.0113639831543,
							288.0539779663086
						]
					},
					"springIds": [
						"5",
						"6",
						"21",
						"22",
						"24",
						"40"
					],
					"bodyIds": [
						"1"
					]
				}
			]
		},
		{
			"id": "6",
			"particles": [
				{
					"id": "11",
					"position": {
						"vector": [
							473.0113639831543,
							288.0539779663086
						]
					},
					"springIds": [
						"5",
						"6",
						"21",
						"22",
						"24",
						"40"
					],
					"bodyIds": [
						"1"
					]
				},
				{
					"id": "10",
					"position": {
						"vector": [
							500.0113639831543,
							307.0539779663086
						]
					},
					"springIds": [
						"6",
						"7",
						"39",
						"41",
						"42"
					],
					"bodyIds": [
						"1"
					]
				}
			]
		},
		{
			"id": "7",
			"particles": [
				{
					"id": "10",
					"position": {
						"vector": [
							500.0113639831543,
							307.0539779663086
						]
					},
					"springIds": [
						"6",
						"7",
						"39",
						"41",
						"42"
					],
					"bodyIds": [
						"1"
					]
				},
				{
					"id": "9",
					"position": {
						"vector": [
							518.0113639831543,
							326.0539779663086
						]
					},
					"springIds": [
						"7",
						"8",
						"43"
					],
					"bodyIds": [
						"1"
					]
				}
			]
		},
		{
			"id": "8",
			"particles": [
				{
					"id": "9",
					"position": {
						"vector": [
							518.0113639831543,
							326.0539779663086
						]
					},
					"springIds": [
						"7",
						"8",
						"43"
					],
					"bodyIds": [
						"1"
					]
				},
				{
					"id": "8",
					"position": {
						"vector": [
							511.0113639831543,
							352.0539779663086
						]
					},
					"springIds": [
						"8",
						"9",
						"42"
					],
					"bodyIds": [
						"1"
					]
				}
			]
		},
		{
			"id": "9",
			"particles": [
				{
					"id": "8",
					"position": {
						"vector": [
							511.0113639831543,
							352.0539779663086
						]
					},
					"springIds": [
						"8",
						"9",
						"42"
					],
					"bodyIds": [
						"1"
					]
				},
				{
					"id": "7",
					"position": {
						"vector": [
							474.0113639831543,
							359.0539779663086
						]
					},
					"springIds": [
						"9",
						"10",
						"40",
						"41",
						"43"
					],
					"bodyIds": [
						"1"
					]
				}
			]
		},
		{
			"id": "10",
			"particles": [
				{
					"id": "7",
					"position": {
						"vector": [
							474.0113639831543,
							359.0539779663086
						]
					},
					"springIds": [
						"9",
						"10",
						"40",
						"41",
						"43"
					],
					"bodyIds": [
						"1"
					]
				},
				{
					"id": "6",
					"position": {
						"vector": [
							449.0113639831543,
							336.0539779663086
						]
					},
					"springIds": [
						"10",
						"11",
						"20",
						"21",
						"38",
						"39"
					],
					"bodyIds": [
						"1"
					]
				}
			]
		},
		{
			"id": "11",
			"particles": [
				{
					"id": "6",
					"position": {
						"vector": [
							449.0113639831543,
							336.0539779663086
						]
					},
					"springIds": [
						"10",
						"11",
						"20",
						"21",
						"38",
						"39"
					],
					"bodyIds": [
						"1"
					]
				},
				{
					"id": "5",
					"position": {
						"vector": [
							420.0113639831543,
							360.0539779663086
						]
					},
					"springIds": [
						"11",
						"12",
						"34",
						"36",
						"37"
					],
					"bodyIds": [
						"1"
					]
				}
			]
		},
		{
			"id": "12",
			"particles": [
				{
					"id": "5",
					"position": {
						"vector": [
							420.0113639831543,
							360.0539779663086
						]
					},
					"springIds": [
						"11",
						"12",
						"34",
						"36",
						"37"
					],
					"bodyIds": [
						"1"
					]
				},
				{
					"id": "4",
					"position": {
						"vector": [
							384.0113639831543,
							355.0539779663086
						]
					},
					"springIds": [
						"12",
						"13",
						"35"
					],
					"bodyIds": [
						"1"
					]
				}
			]
		},
		{
			"id": "13",
			"particles": [
				{
					"id": "4",
					"position": {
						"vector": [
							384.0113639831543,
							355.0539779663086
						]
					},
					"springIds": [
						"12",
						"13",
						"35"
					],
					"bodyIds": [
						"1"
					]
				},
				{
					"id": "3",
					"position": {
						"vector": [
							373.0113639831543,
							330.0539779663086
						]
					},
					"springIds": [
						"13",
						"14",
						"36"
					],
					"bodyIds": [
						"1"
					]
				}
			]
		},
		{
			"id": "14",
			"particles": [
				{
					"id": "3",
					"position": {
						"vector": [
							373.0113639831543,
							330.0539779663086
						]
					},
					"springIds": [
						"13",
						"14",
						"36"
					],
					"bodyIds": [
						"1"
					]
				},
				{
					"id": "2",
					"position": {
						"vector": [
							390.0113639831543,
							308.0539779663086
						]
					},
					"springIds": [
						"14",
						"15",
						"34",
						"35",
						"38"
					],
					"bodyIds": [
						"1"
					]
				}
			]
		},
		{
			"id": "15",
			"particles": [
				{
					"id": "2",
					"position": {
						"vector": [
							390.0113639831543,
							308.0539779663086
						]
					},
					"springIds": [
						"14",
						"15",
						"34",
						"35",
						"38"
					],
					"bodyIds": [
						"1"
					]
				},
				{
					"id": "1",
					"position": {
						"vector": [
							419.0113639831543,
							289.0539779663086
						]
					},
					"springIds": [
						"15",
						"16",
						"20",
						"22",
						"23",
						"37"
					],
					"bodyIds": [
						"1"
					]
				}
			]
		},
		{
			"id": "16",
			"particles": [
				{
					"id": "1",
					"position": {
						"vector": [
							419.0113639831543,
							289.0539779663086
						]
					},
					"springIds": [
						"15",
						"16",
						"20",
						"22",
						"23",
						"37"
					],
					"bodyIds": [
						"1"
					]
				},
				{
					"id": "19",
					"position": {
						"vector": [
							417.0113639831543,
							248.0539779663086
						]
					},
					"springIds": [
						"16",
						"17",
						"24",
						"25",
						"31"
					],
					"bodyIds": [
						"1"
					]
				}
			]
		},
		{
			"id": "17",
			"particles": [
				{
					"id": "19",
					"position": {
						"vector": [
							417.0113639831543,
							248.0539779663086
						]
					},
					"springIds": [
						"16",
						"17",
						"24",
						"25",
						"31"
					],
					"bodyIds": [
						"1"
					]
				},
				{
					"id": "18",
					"position": {
						"vector": [
							417.0113639831543,
							210.0539779663086
						]
					},
					"springIds": [
						"17",
						"18",
						"26",
						"27",
						"32"
					],
					"bodyIds": [
						"1"
					]
				}
			]
		},
		{
			"id": "18",
			"particles": [
				{
					"id": "18",
					"position": {
						"vector": [
							417.0113639831543,
							210.0539779663086
						]
					},
					"springIds": [
						"17",
						"18",
						"26",
						"27",
						"32"
					],
					"bodyIds": [
						"1"
					]
				},
				{
					"id": "17",
					"position": {
						"vector": [
							420.0113639831543,
							168.0539779663086
						]
					},
					"springIds": [
						"18",
						"19",
						"28",
						"29",
						"33"
					],
					"bodyIds": [
						"1"
					]
				}
			]
		},
		{
			"id": "19",
			"particles": [
				{
					"id": "17",
					"position": {
						"vector": [
							420.0113639831543,
							168.0539779663086
						]
					},
					"springIds": [
						"18",
						"19",
						"28",
						"29",
						"33"
					],
					"bodyIds": [
						"1"
					]
				},
				{
					"id": "16",
					"position": {
						"vector": [
							431.0113639831543,
							144.0539779663086
						]
					},
					"springIds": [
						"1",
						"19",
						"30"
					],
					"bodyIds": [
						"1"
					]
				}
			]
		},
		{
			"id": "20",
			"particles": [
				{
					"id": "1",
					"position": {
						"vector": [
							419.0113639831543,
							289.0539779663086
						]
					},
					"springIds": [
						"15",
						"16",
						"20",
						"22",
						"23",
						"37"
					],
					"bodyIds": [
						"1"
					]
				},
				{
					"id": "6",
					"position": {
						"vector": [
							449.0113639831543,
							336.0539779663086
						]
					},
					"springIds": [
						"10",
						"11",
						"20",
						"21",
						"38",
						"39"
					],
					"bodyIds": [
						"1"
					]
				}
			]
		},
		{
			"id": "21",
			"particles": [
				{
					"id": "6",
					"position": {
						"vector": [
							449.0113639831543,
							336.0539779663086
						]
					},
					"springIds": [
						"10",
						"11",
						"20",
						"21",
						"38",
						"39"
					],
					"bodyIds": [
						"1"
					]
				},
				{
					"id": "11",
					"position": {
						"vector": [
							473.0113639831543,
							288.0539779663086
						]
					},
					"springIds": [
						"5",
						"6",
						"21",
						"22",
						"24",
						"40"
					],
					"bodyIds": [
						"1"
					]
				}
			]
		},
		{
			"id": "22",
			"particles": [
				{
					"id": "11",
					"position": {
						"vector": [
							473.0113639831543,
							288.0539779663086
						]
					},
					"springIds": [
						"5",
						"6",
						"21",
						"22",
						"24",
						"40"
					],
					"bodyIds": [
						"1"
					]
				},
				{
					"id": "1",
					"position": {
						"vector": [
							419.0113639831543,
							289.0539779663086
						]
					},
					"springIds": [
						"15",
						"16",
						"20",
						"22",
						"23",
						"37"
					],
					"bodyIds": [
						"1"
					]
				}
			]
		},
		{
			"id": "23",
			"particles": [
				{
					"id": "1",
					"position": {
						"vector": [
							419.0113639831543,
							289.0539779663086
						]
					},
					"springIds": [
						"15",
						"16",
						"20",
						"22",
						"23",
						"37"
					],
					"bodyIds": [
						"1"
					]
				},
				{
					"id": "12",
					"position": {
						"vector": [
							472.0113639831543,
							247.0539779663086
						]
					},
					"springIds": [
						"4",
						"5",
						"23",
						"26",
						"31"
					],
					"bodyIds": [
						"1"
					]
				}
			]
		},
		{
			"id": "24",
			"particles": [
				{
					"id": "19",
					"position": {
						"vector": [
							417.0113639831543,
							248.0539779663086
						]
					},
					"springIds": [
						"16",
						"17",
						"24",
						"25",
						"31"
					],
					"bodyIds": [
						"1"
					]
				},
				{
					"id": "11",
					"position": {
						"vector": [
							473.0113639831543,
							288.0539779663086
						]
					},
					"springIds": [
						"5",
						"6",
						"21",
						"22",
						"24",
						"40"
					],
					"bodyIds": [
						"1"
					]
				}
			]
		},
		{
			"id": "25",
			"particles": [
				{
					"id": "19",
					"position": {
						"vector": [
							417.0113639831543,
							248.0539779663086
						]
					},
					"springIds": [
						"16",
						"17",
						"24",
						"25",
						"31"
					],
					"bodyIds": [
						"1"
					]
				},
				{
					"id": "13",
					"position": {
						"vector": [
							473.0113639831543,
							214.0539779663086
						]
					},
					"springIds": [
						"3",
						"4",
						"25",
						"28",
						"32"
					],
					"bodyIds": [
						"1"
					]
				}
			]
		},
		{
			"id": "26",
			"particles": [
				{
					"id": "12",
					"position": {
						"vector": [
							472.0113639831543,
							247.0539779663086
						]
					},
					"springIds": [
						"4",
						"5",
						"23",
						"26",
						"31"
					],
					"bodyIds": [
						"1"
					]
				},
				{
					"id": "18",
					"position": {
						"vector": [
							417.0113639831543,
							210.0539779663086
						]
					},
					"springIds": [
						"17",
						"18",
						"26",
						"27",
						"32"
					],
					"bodyIds": [
						"1"
					]
				}
			]
		},
		{
			"id": "27",
			"particles": [
				{
					"id": "18",
					"position": {
						"vector": [
							417.0113639831543,
							210.0539779663086
						]
					},
					"springIds": [
						"17",
						"18",
						"26",
						"27",
						"32"
					],
					"bodyIds": [
						"1"
					]
				},
				{
					"id": "14",
					"position": {
						"vector": [
							472.0113639831543,
							167.0539779663086
						]
					},
					"springIds": [
						"2",
						"3",
						"27",
						"30",
						"33"
					],
					"bodyIds": [
						"1"
					]
				}
			]
		},
		{
			"id": "28",
			"particles": [
				{
					"id": "13",
					"position": {
						"vector": [
							473.0113639831543,
							214.0539779663086
						]
					},
					"springIds": [
						"3",
						"4",
						"25",
						"28",
						"32"
					],
					"bodyIds": [
						"1"
					]
				},
				{
					"id": "17",
					"position": {
						"vector": [
							420.0113639831543,
							168.0539779663086
						]
					},
					"springIds": [
						"18",
						"19",
						"28",
						"29",
						"33"
					],
					"bodyIds": [
						"1"
					]
				}
			]
		},
		{
			"id": "29",
			"particles": [
				{
					"id": "17",
					"position": {
						"vector": [
							420.0113639831543,
							168.0539779663086
						]
					},
					"springIds": [
						"18",
						"19",
						"28",
						"29",
						"33"
					],
					"bodyIds": [
						"1"
					]
				},
				{
					"id": "15",
					"position": {
						"vector": [
							455.0113639831543,
							144.0539779663086
						]
					},
					"springIds": [
						"1",
						"2",
						"29"
					],
					"bodyIds": [
						"1"
					]
				}
			]
		},
		{
			"id": "30",
			"particles": [
				{
					"id": "14",
					"position": {
						"vector": [
							472.0113639831543,
							167.0539779663086
						]
					},
					"springIds": [
						"2",
						"3",
						"27",
						"30",
						"33"
					],
					"bodyIds": [
						"1"
					]
				},
				{
					"id": "16",
					"position": {
						"vector": [
							431.0113639831543,
							144.0539779663086
						]
					},
					"springIds": [
						"1",
						"19",
						"30"
					],
					"bodyIds": [
						"1"
					]
				}
			]
		},
		{
			"id": "31",
			"particles": [
				{
					"id": "19",
					"position": {
						"vector": [
							417.0113639831543,
							248.0539779663086
						]
					},
					"springIds": [
						"16",
						"17",
						"24",
						"25",
						"31"
					],
					"bodyIds": [
						"1"
					]
				},
				{
					"id": "12",
					"position": {
						"vector": [
							472.0113639831543,
							247.0539779663086
						]
					},
					"springIds": [
						"4",
						"5",
						"23",
						"26",
						"31"
					],
					"bodyIds": [
						"1"
					]
				}
			]
		},
		{
			"id": "32",
			"particles": [
				{
					"id": "18",
					"position": {
						"vector": [
							417.0113639831543,
							210.0539779663086
						]
					},
					"springIds": [
						"17",
						"18",
						"26",
						"27",
						"32"
					],
					"bodyIds": [
						"1"
					]
				},
				{
					"id": "13",
					"position": {
						"vector": [
							473.0113639831543,
							214.0539779663086
						]
					},
					"springIds": [
						"3",
						"4",
						"25",
						"28",
						"32"
					],
					"bodyIds": [
						"1"
					]
				}
			]
		},
		{
			"id": "33",
			"particles": [
				{
					"id": "17",
					"position": {
						"vector": [
							420.0113639831543,
							168.0539779663086
						]
					},
					"springIds": [
						"18",
						"19",
						"28",
						"29",
						"33"
					],
					"bodyIds": [
						"1"
					]
				},
				{
					"id": "14",
					"position": {
						"vector": [
							472.0113639831543,
							167.0539779663086
						]
					},
					"springIds": [
						"2",
						"3",
						"27",
						"30",
						"33"
					],
					"bodyIds": [
						"1"
					]
				}
			]
		},
		{
			"id": "34",
			"particles": [
				{
					"id": "5",
					"position": {
						"vector": [
							420.0113639831543,
							360.0539779663086
						]
					},
					"springIds": [
						"11",
						"12",
						"34",
						"36",
						"37"
					],
					"bodyIds": [
						"1"
					]
				},
				{
					"id": "2",
					"position": {
						"vector": [
							390.0113639831543,
							308.0539779663086
						]
					},
					"springIds": [
						"14",
						"15",
						"34",
						"35",
						"38"
					],
					"bodyIds": [
						"1"
					]
				}
			]
		},
		{
			"id": "35",
			"particles": [
				{
					"id": "4",
					"position": {
						"vector": [
							384.0113639831543,
							355.0539779663086
						]
					},
					"springIds": [
						"12",
						"13",
						"35"
					],
					"bodyIds": [
						"1"
					]
				},
				{
					"id": "2",
					"position": {
						"vector": [
							390.0113639831543,
							308.0539779663086
						]
					},
					"springIds": [
						"14",
						"15",
						"34",
						"35",
						"38"
					],
					"bodyIds": [
						"1"
					]
				}
			]
		},
		{
			"id": "36",
			"particles": [
				{
					"id": "3",
					"position": {
						"vector": [
							373.0113639831543,
							330.0539779663086
						]
					},
					"springIds": [
						"13",
						"14",
						"36"
					],
					"bodyIds": [
						"1"
					]
				},
				{
					"id": "5",
					"position": {
						"vector": [
							420.0113639831543,
							360.0539779663086
						]
					},
					"springIds": [
						"11",
						"12",
						"34",
						"36",
						"37"
					],
					"bodyIds": [
						"1"
					]
				}
			]
		},
		{
			"id": "37",
			"particles": [
				{
					"id": "1",
					"position": {
						"vector": [
							419.0113639831543,
							289.0539779663086
						]
					},
					"springIds": [
						"15",
						"16",
						"20",
						"22",
						"23",
						"37"
					],
					"bodyIds": [
						"1"
					]
				},
				{
					"id": "5",
					"position": {
						"vector": [
							420.0113639831543,
							360.0539779663086
						]
					},
					"springIds": [
						"11",
						"12",
						"34",
						"36",
						"37"
					],
					"bodyIds": [
						"1"
					]
				}
			]
		},
		{
			"id": "38",
			"particles": [
				{
					"id": "2",
					"position": {
						"vector": [
							390.0113639831543,
							308.0539779663086
						]
					},
					"springIds": [
						"14",
						"15",
						"34",
						"35",
						"38"
					],
					"bodyIds": [
						"1"
					]
				},
				{
					"id": "6",
					"position": {
						"vector": [
							449.0113639831543,
							336.0539779663086
						]
					},
					"springIds": [
						"10",
						"11",
						"20",
						"21",
						"38",
						"39"
					],
					"bodyIds": [
						"1"
					]
				}
			]
		},
		{
			"id": "39",
			"particles": [
				{
					"id": "6",
					"position": {
						"vector": [
							449.0113639831543,
							336.0539779663086
						]
					},
					"springIds": [
						"10",
						"11",
						"20",
						"21",
						"38",
						"39"
					],
					"bodyIds": [
						"1"
					]
				},
				{
					"id": "10",
					"position": {
						"vector": [
							500.0113639831543,
							307.0539779663086
						]
					},
					"springIds": [
						"6",
						"7",
						"39",
						"41",
						"42"
					],
					"bodyIds": [
						"1"
					]
				}
			]
		},
		{
			"id": "40",
			"particles": [
				{
					"id": "11",
					"position": {
						"vector": [
							473.0113639831543,
							288.0539779663086
						]
					},
					"springIds": [
						"5",
						"6",
						"21",
						"22",
						"24",
						"40"
					],
					"bodyIds": [
						"1"
					]
				},
				{
					"id": "7",
					"position": {
						"vector": [
							474.0113639831543,
							359.0539779663086
						]
					},
					"springIds": [
						"9",
						"10",
						"40",
						"41",
						"43"
					],
					"bodyIds": [
						"1"
					]
				}
			]
		},
		{
			"id": "41",
			"particles": [
				{
					"id": "10",
					"position": {
						"vector": [
							500.0113639831543,
							307.0539779663086
						]
					},
					"springIds": [
						"6",
						"7",
						"39",
						"41",
						"42"
					],
					"bodyIds": [
						"1"
					]
				},
				{
					"id": "7",
					"position": {
						"vector": [
							474.0113639831543,
							359.0539779663086
						]
					},
					"springIds": [
						"9",
						"10",
						"40",
						"41",
						"43"
					],
					"bodyIds": [
						"1"
					]
				}
			]
		},
		{
			"id": "42",
			"particles": [
				{
					"id": "10",
					"position": {
						"vector": [
							500.0113639831543,
							307.0539779663086
						]
					},
					"springIds": [
						"6",
						"7",
						"39",
						"41",
						"42"
					],
					"bodyIds": [
						"1"
					]
				},
				{
					"id": "8",
					"position": {
						"vector": [
							511.0113639831543,
							352.0539779663086
						]
					},
					"springIds": [
						"8",
						"9",
						"42"
					],
					"bodyIds": [
						"1"
					]
				}
			]
		},
		{
			"id": "43",
			"particles": [
				{
					"id": "9",
					"position": {
						"vector": [
							518.0113639831543,
							326.0539779663086
						]
					},
					"springIds": [
						"7",
						"8",
						"43"
					],
					"bodyIds": [
						"1"
					]
				},
				{
					"id": "7",
					"position": {
						"vector": [
							474.0113639831543,
							359.0539779663086
						]
					},
					"springIds": [
						"9",
						"10",
						"40",
						"41",
						"43"
					],
					"bodyIds": [
						"1"
					]
				}
			]
		}
	]
}
